[
  {
    "comuna": "Colina",
    "tipo": "",
    "operacion": "",
    "precioUF": 0,
    "precioCLP": 0,
    "dormitorios": "5",
    "banos": "4",
    "superficie": null,
    "estacionamientos": null,
    "bodegas": null,
    "descripcion": "",
    "link": "https://nexxospropiedades.cl/fichaPropiedad.aspx?i=134491",
    "source": "Nexxos",
    "fechaActualizacion": "2026-01-31T11:13:37.636Z"
  },
  {
    "comuna": "Ñuñoa",
    "tipo": "",
    "operacion": "",
    "precioUF": 0,
    "precioCLP": 0,
    "dormitorios": "0",
    "banos": "1",
    "superficie": null,
    "estacionamientos": null,
    "bodegas": null,
    "descripcion": "",
    "link": "https://nexxospropiedades.cl/fichaPropiedad.aspx?i=134462",
    "source": "Nexxos",
    "fechaActualizacion": "2026-01-31T11:13:37.636Z"
  },
  {
    "comuna": "Providencia",
    "tipo": "",
    "operacion": "",
    "precioUF": 0,
    "precioCLP": 0,
    "dormitorios": "3",
    "banos": "2",
    "superficie": null,
    "estacionamientos": null,
    "bodegas": null,
    "descripcion": "",
    "link": "https://nexxospropiedades.cl/fichaPropiedad.aspx?i=134458",
    "source": "Nexxos",
    "fechaActualizacion": "2026-01-31T11:13:37.636Z"
  },
  {
    "comuna": "Ñuñoa",
    "tipo": "",
    "operacion": "",
    "precioUF": 0,
    "precioCLP": 0,
    "dormitorios": "2",
    "banos": "2",
    "superficie": null,
    "estacionamientos": null,
    "bodegas": null,
    "descripcion": "",
    "link": "https://nexxospropiedades.cl/fichaPropiedad.aspx?i=134451",
    "source": "Nexxos",
    "fechaActualizacion": "2026-01-31T11:13:37.636Z"
  },
  {
    "comuna": "Las Condes",
    "tipo": "",
    "operacion": "",
    "precioUF": 0,
    "precioCLP": 0,
    "dormitorios": "4",
    "banos": "3",
    "superficie": null,
    "estacionamientos": null,
    "bodegas": null,
    "descripcion": "",
    "link": "https://nexxospropiedades.cl/fichaPropiedad.aspx?i=134379",
    "source": "Nexxos",
    "fechaActualizacion": "2026-01-31T11:13:37.636Z"
  },
  {
    "comuna": "San Miguel",
    "tipo": "",
    "operacion": "",
    "precioUF": 0,
    "precioCLP": 0,
    "dormitorios": "2",
    "banos": "1",
    "superficie": null,
    "estacionamientos": null,
    "bodegas": null,
    "descripcion": "",
    "link": "https://nexxospropiedades.cl/fichaPropiedad.aspx?i=134375",
    "source": "Nexxos",
    "fechaActualizacion": "2026-01-31T11:13:37.636Z"
  },
  {
    "comuna": "Santiago",
    "tipo": "",
    "operacion": "",
    "precioUF": 0,
    "precioCLP": 0,
    "dormitorios": "1",
    "banos": "1",
    "superficie": null,
    "estacionamientos": null,
    "bodegas": null,
    "descripcion": "",
    "link": "https://nexxospropiedades.cl/fichaPropiedad.aspx?i=134372",
    "source": "Nexxos",
    "fechaActualizacion": "2026-01-31T11:13:37.636Z"
  },
  {
    "comuna": "Ñuñoa",
    "tipo": "",
    "operacion": "",
    "precioUF": 0,
    "precioCLP": 0,
    "dormitorios": "1",
    "banos": "1",
    "superficie": null,
    "estacionamientos": null,
    "bodegas": null,
    "descripcion": "",
    "link": "https://nexxospropiedades.cl/fichaPropiedad.aspx?i=134363",
    "source": "Nexxos",
    "fechaActualizacion": "2026-01-31T11:13:37.636Z"
  },
  {
    "comuna": "Ñuñoa",
    "tipo": "",
    "operacion": "",
    "precioUF": 0,
    "precioCLP": 0,
    "dormitorios": "3",
    "banos": "2",
    "superficie": null,
    "estacionamientos": null,
    "bodegas": null,
    "descripcion": "",
    "link": "https://nexxospropiedades.cl/fichaPropiedad.aspx?i=134351",
    "source": "Nexxos",
    "fechaActualizacion": "2026-01-31T11:13:37.636Z"
  },
  {
    "comuna": "Lo Barnechea",
    "tipo": "",
    "operacion": "",
    "precioUF": 0,
    "precioCLP": 0,
    "dormitorios": "4",
    "banos": "4",
    "superficie": null,
    "estacionamientos": null,
    "bodegas": null,
    "descripcion": "",
    "link": "https://nexxospropiedades.cl/fichaPropiedad.aspx?i=134347",
    "source": "Nexxos",
    "fechaActualizacion": "2026-01-31T11:13:37.636Z"
  },
  {
    "comuna": "Santiago",
    "tipo": "",
    "operacion": "",
    "precioUF": 0,
    "precioCLP": 0,
    "dormitorios": "0",
    "banos": "1",
    "superficie": null,
    "estacionamientos": null,
    "bodegas": null,
    "descripcion": "",
    "link": "https://nexxospropiedades.cl/fichaPropiedad.aspx?i=134341",
    "source": "Nexxos",
    "fechaActualizacion": "2026-01-31T11:13:37.636Z"
  },
  {
    "comuna": "La Florida",
    "tipo": "",
    "operacion": "",
    "precioUF": 0,
    "precioCLP": 0,
    "dormitorios": "4",
    "banos": "4",
    "superficie": null,
    "estacionamientos": null,
    "bodegas": null,
    "descripcion": "",
    "link": "https://nexxospropiedades.cl/fichaPropiedad.aspx?i=134337",
    "source": "Nexxos",
    "fechaActualizacion": "2026-01-31T11:13:37.636Z"
  },
  {
    "comuna": "Providencia",
    "tipo": "",
    "operacion": "",
    "precioUF": 0,
    "precioCLP": 0,
    "dormitorios": "0",
    "banos": "4",
    "superficie": null,
    "estacionamientos": null,
    "bodegas": null,
    "descripcion": "",
    "link": "https://nexxospropiedades.cl/fichaPropiedad.aspx?i=134332",
    "source": "Nexxos",
    "fechaActualizacion": "2026-01-31T11:13:37.636Z"
  },
  {
    "comuna": "La Cisterna",
    "tipo": "",
    "operacion": "",
    "precioUF": 0,
    "precioCLP": 0,
    "dormitorios": "5",
    "banos": "3",
    "superficie": null,
    "estacionamientos": null,
    "bodegas": null,
    "descripcion": "",
    "link": "https://nexxospropiedades.cl/fichaPropiedad.aspx?i=134327",
    "source": "Nexxos",
    "fechaActualizacion": "2026-01-31T11:13:37.636Z"
  },
  {
    "comuna": "Ñuñoa",
    "tipo": "",
    "operacion": "",
    "precioUF": 0,
    "precioCLP": 0,
    "dormitorios": "2",
    "banos": "2",
    "superficie": null,
    "estacionamientos": null,
    "bodegas": null,
    "descripcion": "",
    "link": "https://nexxospropiedades.cl/fichaPropiedad.aspx?i=134300",
    "source": "Nexxos",
    "fechaActualizacion": "2026-01-31T11:13:37.636Z"
  },
  {
    "comuna": "Estación Central",
    "tipo": "",
    "operacion": "",
    "precioUF": 0,
    "precioCLP": 0,
    "dormitorios": "0",
    "banos": "2",
    "superficie": null,
    "estacionamientos": null,
    "bodegas": null,
    "descripcion": "",
    "link": "https://nexxospropiedades.cl/fichaPropiedad.aspx?i=134286",
    "source": "Nexxos",
    "fechaActualizacion": "2026-01-31T11:13:37.636Z"
  },
  {
    "comuna": "Santiago",
    "tipo": "",
    "operacion": "",
    "precioUF": 0,
    "precioCLP": 0,
    "dormitorios": "1",
    "banos": "1",
    "superficie": null,
    "estacionamientos": null,
    "bodegas": null,
    "descripcion": "",
    "link": "https://nexxospropiedades.cl/fichaPropiedad.aspx?i=134283",
    "source": "Nexxos",
    "fechaActualizacion": "2026-01-31T11:13:37.636Z"
  },
  {
    "comuna": "San Miguel",
    "tipo": "",
    "operacion": "",
    "precioUF": 0,
    "precioCLP": 0,
    "dormitorios": "2",
    "banos": "2",
    "superficie": null,
    "estacionamientos": null,
    "bodegas": null,
    "descripcion": "",
    "link": "https://nexxospropiedades.cl/fichaPropiedad.aspx?i=134282",
    "source": "Nexxos",
    "fechaActualizacion": "2026-01-31T11:13:37.636Z"
  },
  {
    "comuna": "San José de Maipo",
    "tipo": "",
    "operacion": "",
    "precioUF": 0,
    "precioCLP": 0,
    "dormitorios": "4",
    "banos": "2",
    "superficie": null,
    "estacionamientos": null,
    "bodegas": null,
    "descripcion": "",
    "link": "https://nexxospropiedades.cl/fichaPropiedad.aspx?i=134194",
    "source": "Nexxos",
    "fechaActualizacion": "2026-01-31T11:13:37.636Z"
  },
  {
    "comuna": "Renca",
    "tipo": "",
    "operacion": "",
    "precioUF": 0,
    "precioCLP": 0,
    "dormitorios": "3",
    "banos": "2",
    "superficie": null,
    "estacionamientos": null,
    "bodegas": null,
    "descripcion": "",
    "link": "https://nexxospropiedades.cl/fichaPropiedad.aspx?i=134182",
    "source": "Nexxos",
    "fechaActualizacion": "2026-01-31T11:13:37.636Z"
  },
  {
    "comuna": "Cerrillos",
    "tipo": "",
    "operacion": "",
    "precioUF": 0,
    "precioCLP": 0,
    "dormitorios": "4",
    "banos": "4",
    "superficie": null,
    "estacionamientos": null,
    "bodegas": null,
    "descripcion": "",
    "link": "https://nexxospropiedades.cl/fichaPropiedad.aspx?i=134178",
    "source": "Nexxos",
    "fechaActualizacion": "2026-01-31T11:13:37.636Z"
  },
  {
    "comuna": "Colina",
    "tipo": "",
    "operacion": "",
    "precioUF": 0,
    "precioCLP": 0,
    "dormitorios": "6",
    "banos": "4",
    "superficie": null,
    "estacionamientos": null,
    "bodegas": null,
    "descripcion": "",
    "link": "https://nexxospropiedades.cl/fichaPropiedad.aspx?i=134168",
    "source": "Nexxos",
    "fechaActualizacion": "2026-01-31T11:13:37.636Z"
  },
  {
    "comuna": "Vitacura",
    "tipo": "",
    "operacion": "",
    "precioUF": 0,
    "precioCLP": 0,
    "dormitorios": "3",
    "banos": "3",
    "superficie": null,
    "estacionamientos": null,
    "bodegas": null,
    "descripcion": "",
    "link": "https://nexxospropiedades.cl/fichaPropiedad.aspx?i=134149",
    "source": "Nexxos",
    "fechaActualizacion": "2026-01-31T11:13:37.636Z"
  },
  {
    "comuna": "Las Condes",
    "tipo": "",
    "operacion": "",
    "precioUF": 0,
    "precioCLP": 0,
    "dormitorios": "2",
    "banos": "2",
    "superficie": null,
    "estacionamientos": null,
    "bodegas": null,
    "descripcion": "",
    "link": "https://nexxospropiedades.cl/fichaPropiedad.aspx?i=134138",
    "source": "Nexxos",
    "fechaActualizacion": "2026-01-31T11:13:37.636Z"
  },
  {
    "comuna": "Huechuraba",
    "tipo": "",
    "operacion": "",
    "precioUF": 0,
    "precioCLP": 0,
    "dormitorios": "2",
    "banos": "2",
    "superficie": null,
    "estacionamientos": null,
    "bodegas": null,
    "descripcion": "",
    "link": "https://nexxospropiedades.cl/fichaPropiedad.aspx?i=134136",
    "source": "Nexxos",
    "fechaActualizacion": "2026-01-31T11:13:37.636Z"
  },
  {
    "comuna": "La Florida",
    "tipo": "",
    "operacion": "",
    "precioUF": 0,
    "precioCLP": 0,
    "dormitorios": "2",
    "banos": "1",
    "superficie": null,
    "estacionamientos": null,
    "bodegas": null,
    "descripcion": "",
    "link": "https://nexxospropiedades.cl/fichaPropiedad.aspx?i=134132",
    "source": "Nexxos",
    "fechaActualizacion": "2026-01-31T11:13:37.636Z"
  },
  {
    "comuna": "San Bernardo",
    "tipo": "",
    "operacion": "",
    "precioUF": 0,
    "precioCLP": 0,
    "dormitorios": "3",
    "banos": "2",
    "superficie": null,
    "estacionamientos": null,
    "bodegas": null,
    "descripcion": "",
    "link": "https://nexxospropiedades.cl/fichaPropiedad.aspx?i=134131",
    "source": "Nexxos",
    "fechaActualizacion": "2026-01-31T11:13:37.636Z"
  },
  {
    "comuna": "Santiago",
    "tipo": "",
    "operacion": "",
    "precioUF": 0,
    "precioCLP": 0,
    "dormitorios": "2",
    "banos": "2",
    "superficie": null,
    "estacionamientos": null,
    "bodegas": null,
    "descripcion": "",
    "link": "https://nexxospropiedades.cl/fichaPropiedad.aspx?i=134127",
    "source": "Nexxos",
    "fechaActualizacion": "2026-01-31T11:13:37.636Z"
  },
  {
    "comuna": "Las Condes",
    "tipo": "",
    "operacion": "",
    "precioUF": 0,
    "precioCLP": 0,
    "dormitorios": "4",
    "banos": "5",
    "superficie": null,
    "estacionamientos": null,
    "bodegas": null,
    "descripcion": "",
    "link": "https://nexxospropiedades.cl/fichaPropiedad.aspx?i=134114",
    "source": "Nexxos",
    "fechaActualizacion": "2026-01-31T11:13:37.636Z"
  },
  {
    "comuna": "Quilicura",
    "tipo": "",
    "operacion": "",
    "precioUF": 0,
    "precioCLP": 0,
    "dormitorios": "3",
    "banos": "3",
    "superficie": null,
    "estacionamientos": null,
    "bodegas": null,
    "descripcion": "",
    "link": "https://nexxospropiedades.cl/fichaPropiedad.aspx?i=134111",
    "source": "Nexxos",
    "fechaActualizacion": "2026-01-31T11:13:37.636Z"
  },
  {
    "comuna": "Providencia",
    "tipo": "",
    "operacion": "",
    "precioUF": 0,
    "precioCLP": 0,
    "dormitorios": "2",
    "banos": "1",
    "superficie": null,
    "estacionamientos": null,
    "bodegas": null,
    "descripcion": "",
    "link": "https://nexxospropiedades.cl/fichaPropiedad.aspx?i=134108",
    "source": "Nexxos",
    "fechaActualizacion": "2026-01-31T11:13:37.636Z"
  },
  {
    "comuna": "Puente Alto",
    "tipo": "",
    "operacion": "",
    "precioUF": 0,
    "precioCLP": 0,
    "dormitorios": "3",
    "banos": "3",
    "superficie": null,
    "estacionamientos": null,
    "bodegas": null,
    "descripcion": "",
    "link": "https://nexxospropiedades.cl/fichaPropiedad.aspx?i=134101",
    "source": "Nexxos",
    "fechaActualizacion": "2026-01-31T11:13:37.636Z"
  },
  {
    "comuna": "Macul",
    "tipo": "",
    "operacion": "",
    "precioUF": 0,
    "precioCLP": 0,
    "dormitorios": "2",
    "banos": "2",
    "superficie": null,
    "estacionamientos": null,
    "bodegas": null,
    "descripcion": "",
    "link": "https://nexxospropiedades.cl/fichaPropiedad.aspx?i=134087",
    "source": "Nexxos",
    "fechaActualizacion": "2026-01-31T11:13:37.636Z"
  },
  {
    "comuna": "Ñuñoa",
    "tipo": "",
    "operacion": "",
    "precioUF": 0,
    "precioCLP": 0,
    "dormitorios": "3",
    "banos": "2",
    "superficie": null,
    "estacionamientos": null,
    "bodegas": null,
    "descripcion": "",
    "link": "https://nexxospropiedades.cl/fichaPropiedad.aspx?i=134080",
    "source": "Nexxos",
    "fechaActualizacion": "2026-01-31T11:13:37.636Z"
  },
  {
    "comuna": "Colina",
    "tipo": "",
    "operacion": "",
    "precioUF": 0,
    "precioCLP": 0,
    "dormitorios": "5",
    "banos": "4",
    "superficie": null,
    "estacionamientos": null,
    "bodegas": null,
    "descripcion": "",
    "link": "https://nexxospropiedades.cl/fichaPropiedad.aspx?i=134079",
    "source": "Nexxos",
    "fechaActualizacion": "2026-01-31T11:13:37.636Z"
  },
  {
    "comuna": "Huechuraba",
    "tipo": "",
    "operacion": "",
    "precioUF": 0,
    "precioCLP": 0,
    "dormitorios": "5",
    "banos": "4",
    "superficie": null,
    "estacionamientos": null,
    "bodegas": null,
    "descripcion": "",
    "link": "https://nexxospropiedades.cl/fichaPropiedad.aspx?i=134072",
    "source": "Nexxos",
    "fechaActualizacion": "2026-01-31T11:13:37.636Z"
  },
  {
    "comuna": "Vitacura",
    "tipo": "",
    "operacion": "",
    "precioUF": 0,
    "precioCLP": 0,
    "dormitorios": "4",
    "banos": "3",
    "superficie": null,
    "estacionamientos": null,
    "bodegas": null,
    "descripcion": "",
    "link": "https://nexxospropiedades.cl/fichaPropiedad.aspx?i=134070",
    "source": "Nexxos",
    "fechaActualizacion": "2026-01-31T11:13:37.636Z"
  },
  {
    "comuna": "Las Condes",
    "tipo": "",
    "operacion": "",
    "precioUF": 0,
    "precioCLP": 0,
    "dormitorios": "0",
    "banos": "1",
    "superficie": null,
    "estacionamientos": null,
    "bodegas": null,
    "descripcion": "",
    "link": "https://nexxospropiedades.cl/fichaPropiedad.aspx?i=134043",
    "source": "Nexxos",
    "fechaActualizacion": "2026-01-31T11:13:37.636Z"
  },
  {
    "comuna": "La Florida",
    "tipo": "",
    "operacion": "",
    "precioUF": 0,
    "precioCLP": 0,
    "dormitorios": "2",
    "banos": "2",
    "superficie": null,
    "estacionamientos": null,
    "bodegas": null,
    "descripcion": "",
    "link": "https://nexxospropiedades.cl/fichaPropiedad.aspx?i=134024",
    "source": "Nexxos",
    "fechaActualizacion": "2026-01-31T11:13:37.636Z"
  },
  {
    "comuna": "Lampa",
    "tipo": "",
    "operacion": "",
    "precioUF": 0,
    "precioCLP": 0,
    "dormitorios": "2",
    "banos": "1",
    "superficie": null,
    "estacionamientos": null,
    "bodegas": null,
    "descripcion": "",
    "link": "https://nexxospropiedades.cl/fichaPropiedad.aspx?i=134023",
    "source": "Nexxos",
    "fechaActualizacion": "2026-01-31T11:13:37.636Z"
  },
  {
    "comuna": "La Florida",
    "tipo": "",
    "operacion": "",
    "precioUF": 0,
    "precioCLP": 0,
    "dormitorios": "2",
    "banos": "1",
    "superficie": null,
    "estacionamientos": null,
    "bodegas": null,
    "descripcion": "",
    "link": "https://nexxospropiedades.cl/fichaPropiedad.aspx?i=134020",
    "source": "Nexxos",
    "fechaActualizacion": "2026-01-31T11:13:37.636Z"
  },
  {
    "comuna": "Lo Barnechea",
    "tipo": "",
    "operacion": "",
    "precioUF": 0,
    "precioCLP": 0,
    "dormitorios": "2",
    "banos": "2",
    "superficie": null,
    "estacionamientos": null,
    "bodegas": null,
    "descripcion": "",
    "link": "https://nexxospropiedades.cl/fichaPropiedad.aspx?i=134018",
    "source": "Nexxos",
    "fechaActualizacion": "2026-01-31T11:13:37.636Z"
  },
  {
    "comuna": "Colina",
    "tipo": "",
    "operacion": "",
    "precioUF": 0,
    "precioCLP": 0,
    "dormitorios": "4",
    "banos": "4",
    "superficie": null,
    "estacionamientos": null,
    "bodegas": null,
    "descripcion": "",
    "link": "https://nexxospropiedades.cl/fichaPropiedad.aspx?i=134014",
    "source": "Nexxos",
    "fechaActualizacion": "2026-01-31T11:13:37.636Z"
  },
  {
    "comuna": "Estación Central",
    "tipo": "",
    "operacion": "",
    "precioUF": 0,
    "precioCLP": 0,
    "dormitorios": "2",
    "banos": "1",
    "superficie": null,
    "estacionamientos": null,
    "bodegas": null,
    "descripcion": "",
    "link": "https://nexxospropiedades.cl/fichaPropiedad.aspx?i=134009",
    "source": "Nexxos",
    "fechaActualizacion": "2026-01-31T11:13:37.636Z"
  },
  {
    "comuna": "Santiago",
    "tipo": "",
    "operacion": "",
    "precioUF": 0,
    "precioCLP": 0,
    "dormitorios": "2",
    "banos": "1",
    "superficie": null,
    "estacionamientos": null,
    "bodegas": null,
    "descripcion": "",
    "link": "https://nexxospropiedades.cl/fichaPropiedad.aspx?i=134007",
    "source": "Nexxos",
    "fechaActualizacion": "2026-01-31T11:13:37.636Z"
  },
  {
    "comuna": "San Bernardo",
    "tipo": "",
    "operacion": "",
    "precioUF": 0,
    "precioCLP": 0,
    "dormitorios": "3",
    "banos": "2",
    "superficie": null,
    "estacionamientos": null,
    "bodegas": null,
    "descripcion": "",
    "link": "https://nexxospropiedades.cl/fichaPropiedad.aspx?i=134006",
    "source": "Nexxos",
    "fechaActualizacion": "2026-01-31T11:13:37.636Z"
  },
  {
    "comuna": "San Bernardo",
    "tipo": "",
    "operacion": "",
    "precioUF": 0,
    "precioCLP": 0,
    "dormitorios": "3",
    "banos": "1",
    "superficie": null,
    "estacionamientos": null,
    "bodegas": null,
    "descripcion": "",
    "link": "https://nexxospropiedades.cl/fichaPropiedad.aspx?i=134005",
    "source": "Nexxos",
    "fechaActualizacion": "2026-01-31T11:13:37.636Z"
  },
  {
    "comuna": "Vitacura",
    "tipo": "",
    "operacion": "",
    "precioUF": 0,
    "precioCLP": 0,
    "dormitorios": "4",
    "banos": "4",
    "superficie": null,
    "estacionamientos": null,
    "bodegas": null,
    "descripcion": "",
    "link": "https://nexxospropiedades.cl/fichaPropiedad.aspx?i=134004",
    "source": "Nexxos",
    "fechaActualizacion": "2026-01-31T11:13:37.636Z"
  },
  {
    "comuna": "Peñaflor",
    "tipo": "",
    "operacion": "",
    "precioUF": 0,
    "precioCLP": 0,
    "dormitorios": "3",
    "banos": "1",
    "superficie": null,
    "estacionamientos": null,
    "bodegas": null,
    "descripcion": "",
    "link": "https://nexxospropiedades.cl/fichaPropiedad.aspx?i=134003",
    "source": "Nexxos",
    "fechaActualizacion": "2026-01-31T11:13:37.636Z"
  },
  {
    "comuna": "San Bernardo",
    "tipo": "",
    "operacion": "",
    "precioUF": 0,
    "precioCLP": 0,
    "dormitorios": "3",
    "banos": "2",
    "superficie": null,
    "estacionamientos": null,
    "bodegas": null,
    "descripcion": "",
    "link": "https://nexxospropiedades.cl/fichaPropiedad.aspx?i=134000",
    "source": "Nexxos",
    "fechaActualizacion": "2026-01-31T11:13:37.636Z"
  },
  {
    "comuna": "Ñuñoa",
    "tipo": "",
    "operacion": "",
    "precioUF": 0,
    "precioCLP": 0,
    "dormitorios": "3",
    "banos": "2",
    "superficie": null,
    "estacionamientos": null,
    "bodegas": null,
    "descripcion": "",
    "link": "https://nexxospropiedades.cl/fichaPropiedad.aspx?i=133987",
    "source": "Nexxos",
    "fechaActualizacion": "2026-01-31T11:13:37.636Z"
  },
  {
    "comuna": "Cerrillos",
    "tipo": "",
    "operacion": "",
    "precioUF": 0,
    "precioCLP": 0,
    "dormitorios": "3",
    "banos": "1",
    "superficie": null,
    "estacionamientos": null,
    "bodegas": null,
    "descripcion": "",
    "link": "https://nexxospropiedades.cl/fichaPropiedad.aspx?i=133974",
    "source": "Nexxos",
    "fechaActualizacion": "2026-01-31T11:13:37.636Z"
  },
  {
    "comuna": "Colina",
    "tipo": "",
    "operacion": "",
    "precioUF": 0,
    "precioCLP": 0,
    "dormitorios": "6",
    "banos": "5",
    "superficie": null,
    "estacionamientos": null,
    "bodegas": null,
    "descripcion": "",
    "link": "https://nexxospropiedades.cl/fichaPropiedad.aspx?i=133966",
    "source": "Nexxos",
    "fechaActualizacion": "2026-01-31T11:13:37.636Z"
  },
  {
    "comuna": "Ñuñoa",
    "tipo": "",
    "operacion": "",
    "precioUF": 0,
    "precioCLP": 0,
    "dormitorios": "3",
    "banos": "2",
    "superficie": null,
    "estacionamientos": null,
    "bodegas": null,
    "descripcion": "",
    "link": "https://nexxospropiedades.cl/fichaPropiedad.aspx?i=133909",
    "source": "Nexxos",
    "fechaActualizacion": "2026-01-31T11:13:37.636Z"
  },
  {
    "comuna": "La Cisterna",
    "tipo": "",
    "operacion": "",
    "precioUF": 0,
    "precioCLP": 0,
    "dormitorios": "1",
    "banos": "1",
    "superficie": null,
    "estacionamientos": null,
    "bodegas": null,
    "descripcion": "",
    "link": "https://nexxospropiedades.cl/fichaPropiedad.aspx?i=133907",
    "source": "Nexxos",
    "fechaActualizacion": "2026-01-31T11:13:37.636Z"
  },
  {
    "comuna": "Santiago",
    "tipo": "",
    "operacion": "",
    "precioUF": 0,
    "precioCLP": 0,
    "dormitorios": "1",
    "banos": "1",
    "superficie": null,
    "estacionamientos": null,
    "bodegas": null,
    "descripcion": "",
    "link": "https://nexxospropiedades.cl/fichaPropiedad.aspx?i=133906",
    "source": "Nexxos",
    "fechaActualizacion": "2026-01-31T11:13:37.636Z"
  },
  {
    "comuna": "Macul",
    "tipo": "",
    "operacion": "",
    "precioUF": 0,
    "precioCLP": 0,
    "dormitorios": "2",
    "banos": "2",
    "superficie": null,
    "estacionamientos": null,
    "bodegas": null,
    "descripcion": "",
    "link": "https://nexxospropiedades.cl/fichaPropiedad.aspx?i=133889",
    "source": "Nexxos",
    "fechaActualizacion": "2026-01-31T11:13:37.636Z"
  },
  {
    "comuna": "Providencia",
    "tipo": "",
    "operacion": "",
    "precioUF": 0,
    "precioCLP": 0,
    "dormitorios": "3",
    "banos": "3",
    "superficie": null,
    "estacionamientos": null,
    "bodegas": null,
    "descripcion": "",
    "link": "https://nexxospropiedades.cl/fichaPropiedad.aspx?i=133883",
    "source": "Nexxos",
    "fechaActualizacion": "2026-01-31T11:13:37.636Z"
  },
  {
    "comuna": "Santiago",
    "tipo": "",
    "operacion": "",
    "precioUF": 0,
    "precioCLP": 0,
    "dormitorios": "0",
    "banos": "3",
    "superficie": null,
    "estacionamientos": null,
    "bodegas": null,
    "descripcion": "",
    "link": "https://nexxospropiedades.cl/fichaPropiedad.aspx?i=133880",
    "source": "Nexxos",
    "fechaActualizacion": "2026-01-31T11:13:37.636Z"
  },
  {
    "comuna": "Pudahuel",
    "tipo": "",
    "operacion": "",
    "precioUF": 0,
    "precioCLP": 0,
    "dormitorios": "0",
    "banos": "6",
    "superficie": null,
    "estacionamientos": null,
    "bodegas": null,
    "descripcion": "",
    "link": "https://nexxospropiedades.cl/fichaPropiedad.aspx?i=133871",
    "source": "Nexxos",
    "fechaActualizacion": "2026-01-31T11:13:37.636Z"
  },
  {
    "comuna": "Lo Barnechea",
    "tipo": "",
    "operacion": "",
    "precioUF": 0,
    "precioCLP": 0,
    "dormitorios": "0",
    "banos": "1",
    "superficie": null,
    "estacionamientos": null,
    "bodegas": null,
    "descripcion": "",
    "link": "https://nexxospropiedades.cl/fichaPropiedad.aspx?i=133870",
    "source": "Nexxos",
    "fechaActualizacion": "2026-01-31T11:13:37.636Z"
  },
  {
    "comuna": "Puente Alto",
    "tipo": "",
    "operacion": "",
    "precioUF": 0,
    "precioCLP": 0,
    "dormitorios": "7",
    "banos": "2",
    "superficie": null,
    "estacionamientos": null,
    "bodegas": null,
    "descripcion": "",
    "link": "https://nexxospropiedades.cl/fichaPropiedad.aspx?i=133856",
    "source": "Nexxos",
    "fechaActualizacion": "2026-01-31T11:13:37.636Z"
  },
  {
    "comuna": "Colina",
    "tipo": "",
    "operacion": "",
    "precioUF": 0,
    "precioCLP": 0,
    "dormitorios": "4",
    "banos": "6",
    "superficie": null,
    "estacionamientos": null,
    "bodegas": null,
    "descripcion": "",
    "link": "https://nexxospropiedades.cl/fichaPropiedad.aspx?i=133831",
    "source": "Nexxos",
    "fechaActualizacion": "2026-01-31T11:13:37.636Z"
  },
  {
    "comuna": "Estación Central",
    "tipo": "",
    "operacion": "",
    "precioUF": 0,
    "precioCLP": 0,
    "dormitorios": "1",
    "banos": "1",
    "superficie": null,
    "estacionamientos": null,
    "bodegas": null,
    "descripcion": "",
    "link": "https://nexxospropiedades.cl/fichaPropiedad.aspx?i=133817",
    "source": "Nexxos",
    "fechaActualizacion": "2026-01-31T11:13:37.636Z"
  },
  {
    "comuna": "Estación Central",
    "tipo": "",
    "operacion": "",
    "precioUF": 0,
    "precioCLP": 0,
    "dormitorios": "1",
    "banos": "1",
    "superficie": null,
    "estacionamientos": null,
    "bodegas": null,
    "descripcion": "",
    "link": "https://nexxospropiedades.cl/fichaPropiedad.aspx?i=133816",
    "source": "Nexxos",
    "fechaActualizacion": "2026-01-31T11:13:37.636Z"
  },
  {
    "comuna": "Quinta Normal",
    "tipo": "",
    "operacion": "",
    "precioUF": 0,
    "precioCLP": 0,
    "dormitorios": "1",
    "banos": "1",
    "superficie": null,
    "estacionamientos": null,
    "bodegas": null,
    "descripcion": "",
    "link": "https://nexxospropiedades.cl/fichaPropiedad.aspx?i=133814",
    "source": "Nexxos",
    "fechaActualizacion": "2026-01-31T11:13:37.636Z"
  },
  {
    "comuna": "Quinta Normal",
    "tipo": "",
    "operacion": "",
    "precioUF": 0,
    "precioCLP": 0,
    "dormitorios": "3",
    "banos": "1",
    "superficie": null,
    "estacionamientos": null,
    "bodegas": null,
    "descripcion": "",
    "link": "https://nexxospropiedades.cl/fichaPropiedad.aspx?i=133813",
    "source": "Nexxos",
    "fechaActualizacion": "2026-01-31T11:13:37.636Z"
  },
  {
    "comuna": "Quinta Normal",
    "tipo": "",
    "operacion": "",
    "precioUF": 0,
    "precioCLP": 0,
    "dormitorios": "3",
    "banos": "1",
    "superficie": null,
    "estacionamientos": null,
    "bodegas": null,
    "descripcion": "",
    "link": "https://nexxospropiedades.cl/fichaPropiedad.aspx?i=133812",
    "source": "Nexxos",
    "fechaActualizacion": "2026-01-31T11:13:37.636Z"
  },
  {
    "comuna": "Independencia",
    "tipo": "",
    "operacion": "",
    "precioUF": 0,
    "precioCLP": 0,
    "dormitorios": "2",
    "banos": "2",
    "superficie": null,
    "estacionamientos": null,
    "bodegas": null,
    "descripcion": "",
    "link": "https://nexxospropiedades.cl/fichaPropiedad.aspx?i=133811",
    "source": "Nexxos",
    "fechaActualizacion": "2026-01-31T11:13:37.636Z"
  },
  {
    "comuna": "Macul",
    "tipo": "",
    "operacion": "",
    "precioUF": 0,
    "precioCLP": 0,
    "dormitorios": "2",
    "banos": "2",
    "superficie": null,
    "estacionamientos": null,
    "bodegas": null,
    "descripcion": "",
    "link": "https://nexxospropiedades.cl/fichaPropiedad.aspx?i=133810",
    "source": "Nexxos",
    "fechaActualizacion": "2026-01-31T11:13:37.636Z"
  },
  {
    "comuna": "Santiago",
    "tipo": "",
    "operacion": "",
    "precioUF": 0,
    "precioCLP": 0,
    "dormitorios": "1",
    "banos": "1",
    "superficie": null,
    "estacionamientos": null,
    "bodegas": null,
    "descripcion": "",
    "link": "https://nexxospropiedades.cl/fichaPropiedad.aspx?i=133809",
    "source": "Nexxos",
    "fechaActualizacion": "2026-01-31T11:13:37.636Z"
  },
  {
    "comuna": "San Miguel",
    "tipo": "",
    "operacion": "",
    "precioUF": 0,
    "precioCLP": 0,
    "dormitorios": "1",
    "banos": "1",
    "superficie": null,
    "estacionamientos": null,
    "bodegas": null,
    "descripcion": "",
    "link": "https://nexxospropiedades.cl/fichaPropiedad.aspx?i=133808",
    "source": "Nexxos",
    "fechaActualizacion": "2026-01-31T11:13:37.636Z"
  },
  {
    "comuna": "Ñuñoa",
    "tipo": "",
    "operacion": "",
    "precioUF": 0,
    "precioCLP": 0,
    "dormitorios": "1",
    "banos": "1",
    "superficie": null,
    "estacionamientos": null,
    "bodegas": null,
    "descripcion": "",
    "link": "https://nexxospropiedades.cl/fichaPropiedad.aspx?i=133806",
    "source": "Nexxos",
    "fechaActualizacion": "2026-01-31T11:13:37.636Z"
  },
  {
    "comuna": "Santiago",
    "tipo": "",
    "operacion": "",
    "precioUF": 0,
    "precioCLP": 0,
    "dormitorios": "1",
    "banos": "1",
    "superficie": null,
    "estacionamientos": null,
    "bodegas": null,
    "descripcion": "",
    "link": "https://nexxospropiedades.cl/fichaPropiedad.aspx?i=133805",
    "source": "Nexxos",
    "fechaActualizacion": "2026-01-31T11:13:37.636Z"
  },
  {
    "comuna": "San Miguel",
    "tipo": "",
    "operacion": "",
    "precioUF": 0,
    "precioCLP": 0,
    "dormitorios": "1",
    "banos": "1",
    "superficie": null,
    "estacionamientos": null,
    "bodegas": null,
    "descripcion": "",
    "link": "https://nexxospropiedades.cl/fichaPropiedad.aspx?i=133804",
    "source": "Nexxos",
    "fechaActualizacion": "2026-01-31T11:13:37.636Z"
  },
  {
    "comuna": "Santiago",
    "tipo": "",
    "operacion": "",
    "precioUF": 0,
    "precioCLP": 0,
    "dormitorios": "1",
    "banos": "1",
    "superficie": null,
    "estacionamientos": null,
    "bodegas": null,
    "descripcion": "",
    "link": "https://nexxospropiedades.cl/fichaPropiedad.aspx?i=133801",
    "source": "Nexxos",
    "fechaActualizacion": "2026-01-31T11:13:37.636Z"
  },
  {
    "comuna": "Quinta Normal",
    "tipo": "",
    "operacion": "",
    "precioUF": 0,
    "precioCLP": 0,
    "dormitorios": "2",
    "banos": "1",
    "superficie": null,
    "estacionamientos": null,
    "bodegas": null,
    "descripcion": "",
    "link": "https://nexxospropiedades.cl/fichaPropiedad.aspx?i=133798",
    "source": "Nexxos",
    "fechaActualizacion": "2026-01-31T11:13:37.636Z"
  },
  {
    "comuna": "San Miguel",
    "tipo": "",
    "operacion": "",
    "precioUF": 0,
    "precioCLP": 0,
    "dormitorios": "2",
    "banos": "0",
    "superficie": null,
    "estacionamientos": null,
    "bodegas": null,
    "descripcion": "",
    "link": "https://nexxospropiedades.cl/fichaPropiedad.aspx?i=133797",
    "source": "Nexxos",
    "fechaActualizacion": "2026-01-31T11:13:37.636Z"
  },
  {
    "comuna": "Las Condes",
    "tipo": "",
    "operacion": "",
    "precioUF": 0,
    "precioCLP": 0,
    "dormitorios": "2",
    "banos": "2",
    "superficie": null,
    "estacionamientos": null,
    "bodegas": null,
    "descripcion": "",
    "link": "https://nexxospropiedades.cl/fichaPropiedad.aspx?i=133789",
    "source": "Nexxos",
    "fechaActualizacion": "2026-01-31T11:13:37.636Z"
  },
  {
    "comuna": "Santiago",
    "tipo": "",
    "operacion": "",
    "precioUF": 0,
    "precioCLP": 0,
    "dormitorios": "2",
    "banos": "1",
    "superficie": null,
    "estacionamientos": null,
    "bodegas": null,
    "descripcion": "",
    "link": "https://nexxospropiedades.cl/fichaPropiedad.aspx?i=133781",
    "source": "Nexxos",
    "fechaActualizacion": "2026-01-31T11:13:37.636Z"
  },
  {
    "comuna": "Las Condes",
    "tipo": "",
    "operacion": "",
    "precioUF": 0,
    "precioCLP": 0,
    "dormitorios": "4",
    "banos": "3",
    "superficie": null,
    "estacionamientos": null,
    "bodegas": null,
    "descripcion": "",
    "link": "https://nexxospropiedades.cl/fichaPropiedad.aspx?i=133773",
    "source": "Nexxos",
    "fechaActualizacion": "2026-01-31T11:13:37.636Z"
  },
  {
    "comuna": "Santiago",
    "tipo": "",
    "operacion": "",
    "precioUF": 0,
    "precioCLP": 0,
    "dormitorios": "2",
    "banos": "2",
    "superficie": null,
    "estacionamientos": null,
    "bodegas": null,
    "descripcion": "",
    "link": "https://nexxospropiedades.cl/fichaPropiedad.aspx?i=133757",
    "source": "Nexxos",
    "fechaActualizacion": "2026-01-31T11:13:37.636Z"
  },
  {
    "comuna": "Ñuñoa",
    "tipo": "",
    "operacion": "",
    "precioUF": 0,
    "precioCLP": 0,
    "dormitorios": "4",
    "banos": "3",
    "superficie": null,
    "estacionamientos": null,
    "bodegas": null,
    "descripcion": "",
    "link": "https://nexxospropiedades.cl/fichaPropiedad.aspx?i=133740",
    "source": "Nexxos",
    "fechaActualizacion": "2026-01-31T11:13:37.636Z"
  },
  {
    "comuna": "Macul",
    "tipo": "",
    "operacion": "",
    "precioUF": 0,
    "precioCLP": 0,
    "dormitorios": "1",
    "banos": "1",
    "superficie": null,
    "estacionamientos": null,
    "bodegas": null,
    "descripcion": "",
    "link": "https://nexxospropiedades.cl/fichaPropiedad.aspx?i=133736",
    "source": "Nexxos",
    "fechaActualizacion": "2026-01-31T11:13:37.636Z"
  },
  {
    "comuna": "Ñuñoa",
    "tipo": "",
    "operacion": "",
    "precioUF": 0,
    "precioCLP": 0,
    "dormitorios": "3",
    "banos": "2",
    "superficie": null,
    "estacionamientos": null,
    "bodegas": null,
    "descripcion": "",
    "link": "https://nexxospropiedades.cl/fichaPropiedad.aspx?i=133721",
    "source": "Nexxos",
    "fechaActualizacion": "2026-01-31T11:13:37.636Z"
  },
  {
    "comuna": "Paine",
    "tipo": "",
    "operacion": "",
    "precioUF": 0,
    "precioCLP": 0,
    "dormitorios": "2",
    "banos": "2",
    "superficie": null,
    "estacionamientos": null,
    "bodegas": null,
    "descripcion": "",
    "link": "https://nexxospropiedades.cl/fichaPropiedad.aspx?i=133716",
    "source": "Nexxos",
    "fechaActualizacion": "2026-01-31T11:13:37.636Z"
  },
  {
    "comuna": "Ñuñoa",
    "tipo": "",
    "operacion": "",
    "precioUF": 0,
    "precioCLP": 0,
    "dormitorios": "3",
    "banos": "2",
    "superficie": null,
    "estacionamientos": null,
    "bodegas": null,
    "descripcion": "",
    "link": "https://nexxospropiedades.cl/fichaPropiedad.aspx?i=133692",
    "source": "Nexxos",
    "fechaActualizacion": "2026-01-31T11:13:37.636Z"
  },
  {
    "comuna": "San Bernardo",
    "tipo": "",
    "operacion": "",
    "precioUF": 0,
    "precioCLP": 0,
    "dormitorios": "3",
    "banos": "3",
    "superficie": null,
    "estacionamientos": null,
    "bodegas": null,
    "descripcion": "",
    "link": "https://nexxospropiedades.cl/fichaPropiedad.aspx?i=133688",
    "source": "Nexxos",
    "fechaActualizacion": "2026-01-31T11:13:37.636Z"
  },
  {
    "comuna": "Las Condes",
    "tipo": "",
    "operacion": "",
    "precioUF": 0,
    "precioCLP": 0,
    "dormitorios": "5",
    "banos": "5",
    "superficie": null,
    "estacionamientos": null,
    "bodegas": null,
    "descripcion": "",
    "link": "https://nexxospropiedades.cl/fichaPropiedad.aspx?i=133686",
    "source": "Nexxos",
    "fechaActualizacion": "2026-01-31T11:13:37.636Z"
  },
  {
    "comuna": "Ñuñoa",
    "tipo": "",
    "operacion": "",
    "precioUF": 0,
    "precioCLP": 0,
    "dormitorios": "4",
    "banos": "2",
    "superficie": null,
    "estacionamientos": null,
    "bodegas": null,
    "descripcion": "",
    "link": "https://nexxospropiedades.cl/fichaPropiedad.aspx?i=133685",
    "source": "Nexxos",
    "fechaActualizacion": "2026-01-31T11:13:37.636Z"
  },
  {
    "comuna": "Las Condes",
    "tipo": "",
    "operacion": "",
    "precioUF": 0,
    "precioCLP": 0,
    "dormitorios": "2",
    "banos": "2",
    "superficie": null,
    "estacionamientos": null,
    "bodegas": null,
    "descripcion": "",
    "link": "https://nexxospropiedades.cl/fichaPropiedad.aspx?i=133662",
    "source": "Nexxos",
    "fechaActualizacion": "2026-01-31T11:13:37.636Z"
  },
  {
    "comuna": "Las Condes",
    "tipo": "",
    "operacion": "",
    "precioUF": 0,
    "precioCLP": 0,
    "dormitorios": "6",
    "banos": "5",
    "superficie": null,
    "estacionamientos": null,
    "bodegas": null,
    "descripcion": "",
    "link": "https://nexxospropiedades.cl/fichaPropiedad.aspx?i=133660",
    "source": "Nexxos",
    "fechaActualizacion": "2026-01-31T11:13:37.636Z"
  },
  {
    "comuna": "Ñuñoa",
    "tipo": "",
    "operacion": "",
    "precioUF": 0,
    "precioCLP": 0,
    "dormitorios": "2",
    "banos": "2",
    "superficie": null,
    "estacionamientos": null,
    "bodegas": null,
    "descripcion": "",
    "link": "https://nexxospropiedades.cl/fichaPropiedad.aspx?i=133657",
    "source": "Nexxos",
    "fechaActualizacion": "2026-01-31T11:13:37.636Z"
  },
  {
    "comuna": "Peñalolén",
    "tipo": "",
    "operacion": "",
    "precioUF": 0,
    "precioCLP": 0,
    "dormitorios": "4",
    "banos": "3",
    "superficie": null,
    "estacionamientos": null,
    "bodegas": null,
    "descripcion": "",
    "link": "https://nexxospropiedades.cl/fichaPropiedad.aspx?i=133656",
    "source": "Nexxos",
    "fechaActualizacion": "2026-01-31T11:13:37.636Z"
  },
  {
    "comuna": "La Florida",
    "tipo": "",
    "operacion": "",
    "precioUF": 0,
    "precioCLP": 0,
    "dormitorios": "3",
    "banos": "1",
    "superficie": null,
    "estacionamientos": null,
    "bodegas": null,
    "descripcion": "",
    "link": "https://nexxospropiedades.cl/fichaPropiedad.aspx?i=133648",
    "source": "Nexxos",
    "fechaActualizacion": "2026-01-31T11:13:37.636Z"
  },
  {
    "comuna": "Peñalolén",
    "tipo": "",
    "operacion": "",
    "precioUF": 0,
    "precioCLP": 0,
    "dormitorios": "6",
    "banos": "3",
    "superficie": null,
    "estacionamientos": null,
    "bodegas": null,
    "descripcion": "",
    "link": "https://nexxospropiedades.cl/fichaPropiedad.aspx?i=133644",
    "source": "Nexxos",
    "fechaActualizacion": "2026-01-31T11:13:37.636Z"
  },
  {
    "comuna": "Ñuñoa",
    "tipo": "",
    "operacion": "",
    "precioUF": 0,
    "precioCLP": 0,
    "dormitorios": "2",
    "banos": "2",
    "superficie": null,
    "estacionamientos": null,
    "bodegas": null,
    "descripcion": "",
    "link": "https://nexxospropiedades.cl/fichaPropiedad.aspx?i=133634",
    "source": "Nexxos",
    "fechaActualizacion": "2026-01-31T11:13:37.636Z"
  },
  {
    "comuna": "Santiago",
    "tipo": "",
    "operacion": "",
    "precioUF": 0,
    "precioCLP": 0,
    "dormitorios": "3",
    "banos": "2",
    "superficie": null,
    "estacionamientos": null,
    "bodegas": null,
    "descripcion": "",
    "link": "https://nexxospropiedades.cl/fichaPropiedad.aspx?i=133633",
    "source": "Nexxos",
    "fechaActualizacion": "2026-01-31T11:13:37.636Z"
  },
  {
    "comuna": "Providencia",
    "tipo": "",
    "operacion": "",
    "precioUF": 0,
    "precioCLP": 0,
    "dormitorios": "3",
    "banos": "2",
    "superficie": null,
    "estacionamientos": null,
    "bodegas": null,
    "descripcion": "",
    "link": "https://nexxospropiedades.cl/fichaPropiedad.aspx?i=133630",
    "source": "Nexxos",
    "fechaActualizacion": "2026-01-31T11:13:37.636Z"
  },
  {
    "comuna": "Providencia",
    "tipo": "",
    "operacion": "",
    "precioUF": 0,
    "precioCLP": 0,
    "dormitorios": "3",
    "banos": "2",
    "superficie": null,
    "estacionamientos": null,
    "bodegas": null,
    "descripcion": "",
    "link": "https://nexxospropiedades.cl/fichaPropiedad.aspx?i=133624",
    "source": "Nexxos",
    "fechaActualizacion": "2026-01-31T11:13:37.636Z"
  }
]